clustbench/__init__.py
clustbench/colouriser.py
clustbench/fit_predict.py
clustbench/get_names.py
clustbench/load_dataset.py
clustbench/load_results.py
clustbench/preprocess_data.py
clustbench/score.py
clustering_benchmarks-1.1.6.dist-info/LICENSE
clustering_benchmarks-1.1.6.dist-info/METADATA
clustering_benchmarks-1.1.6.dist-info/WHEEL
clustering_benchmarks-1.1.6.dist-info/top_level.txt
clustering_benchmarks-1.1.6.dist-info/RECORD
