Metadata-Version: 2.1
Name: clustering-benchmarks
Version: 1.1.6
Summary: A Framework for Benchmarking Clustering Algorithms
Home-page: https://clustering-benchmarks.gagolewski.com/
Download-URL: https://github.com/gagolews/clustering-benchmarks
Author: Marek Gagolewski
Author-email: marek@gagolewski.com
Maintainer: Marek Gagolewski
License: GNU Affero General Public License v3
Project-URL: Bug Tracker, https://github.com/gagolews/clustering-benchmarks/issues
Project-URL: Documentation, https://clustering-benchmarks.gagolewski.com/
Project-URL: Source Code, https://github.com/gagolews/clustering-benchmarks
Classifier: Programming Language :: Python
Classifier: Programming Language :: Python :: 3
Classifier: Operating System :: Microsoft :: Windows
Classifier: Operating System :: POSIX
Classifier: Operating System :: Unix
Classifier: Operating System :: MacOS
Classifier: Intended Audience :: Science/Research
Classifier: Intended Audience :: Developers
Classifier: License :: OSI Approved :: GNU Affero General Public License v3
Classifier: Development Status :: 5 - Production/Stable
Classifier: Topic :: Scientific/Engineering
License-File: LICENSE
Requires-Dist: natsort
Requires-Dist: numpy
Requires-Dist: scipy
Requires-Dist: matplotlib
Requires-Dist: pandas
Requires-Dist: cython
Requires-Dist: genieclust
